add_qbt_trackers.py
add_qbt_trackers-0.2.dist-info/METADATA
add_qbt_trackers-0.2.dist-info/WHEEL
add_qbt_trackers-0.2.dist-info/entry_points.txt
add_qbt_trackers-0.2.dist-info/licenses/LICENSE
add_qbt_trackers-0.2.dist-info/RECORD
