Metadata-Version: 2.3
Name: add-qbt-trackers
Version: 0.2
Summary: Add known working trackers to a qBittorrent instance.
Project-URL: Homepage, https://codeberg.org/hyperreal/add-qbt-trackers
Project-URL: Issues, https://codeberg.org/hyperreal/add-qbt-trackers/issues
Author-email: Jeffrey Serio <hyperreal@fedoraproject.org>
Classifier: Environment :: Console
Classifier: License :: OSI Approved :: GNU General Public License v3 or later (GPLv3+)
Classifier: Operating System :: OS Independent
Classifier: Programming Language :: Python :: 3
Classifier: Topic :: Communications :: File Sharing
Classifier: Topic :: Utilities
Requires-Python: >=3.10
Requires-Dist: docopt>=0.6.2
Requires-Dist: qbittorrent-api>=2024.11.70
Requires-Dist: requests>=2.32.3
